takumi_config/__init__.py
takumi_config/_config.py
takumi_config/_settings.py
takumi_config/utils.py
takumi_config-0.1.3.dist-info/top_level.txt
takumi_config-0.1.3.dist-info/METADATA
takumi_config-0.1.3.dist-info/DESCRIPTION.rst
takumi_config-0.1.3.dist-info/metadata.json
takumi_config-0.1.3.dist-info/WHEEL
takumi_config-0.1.3.dist-info/RECORD
