Metadata-Version: 2.0
Name: takumi-config
Version: 0.1.3
Summary: Takumi service framework configuration module
Home-page: https://github.com/elemecreativelab/takumi-config
Author: Eleme Lab
Author-email: imaralla@icloud.com
License: UNKNOWN
Platform: UNKNOWN
Requires-Dist: PyYAML
